opencvutil-0.0.1.dist-info/METADATA
opencvutil-0.0.1.dist-info/WHEEL
opencvutil-0.0.1.dist-info/license_files/LICENSE
opencvutil/py.typed
opencvutil/_opencvutil.pyi
opencvutil/__init__.py
opencvutil/_opencvutil.cp311-win32.pyd
opencvutil-0.0.1.dist-info/RECORD
