Metadata-Version: 2.3
Name: opencvutil
Version: 0.0.1
License-File: LICENSE
Requires-Python: >=3.8
